sysubadminton/__init__.py
sysubadminton/__main__.py
sysubadminton/badminton.py
sysubadminton/random_ua.py
sysubadminton/utils.py
sysubadminton/version.py
sysubadminton-0.4.7.dist-info/LICENSE
sysubadminton-0.4.7.dist-info/METADATA
sysubadminton-0.4.7.dist-info/WHEEL
sysubadminton-0.4.7.dist-info/entry_points.txt
sysubadminton-0.4.7.dist-info/top_level.txt
sysubadminton-0.4.7.dist-info/RECORD
