Metadata-Version: 2.1
Name: sysubadminton
Version: 0.4.7
Summary: 用于中山大学珠海校区羽毛球场的预订
Home-page: https://gist.github.com/834e635e82739ee23d1450357f4fcc6e
Author: SYSUBad
Author-email: sysu@bad.com
License: UNKNOWN
Platform: UNKNOWN
Classifier: License :: OSI Approved :: MIT License
Classifier: Programming Language :: Python :: 3 :: Only
Classifier: Programming Language :: Python :: 3.6
Classifier: Programming Language :: Python :: 3.7
Classifier: Programming Language :: Python :: 3.8
Classifier: Programming Language :: Python :: 3.9
Classifier: Programming Language :: Python :: 3.10
Requires-Python: >=3.6.0
License-File: LICENSE
Requires-Dist: requests
Requires-Dist: backoff
